ihk_ausbildungsnachweis_utilities/__init__.py
ihk_ausbildungsnachweis_utilities/__main__.py
ihk_ausbildungsnachweis_utilities/_version.py
ihk_ausbildungsnachweis_utilities/builder.py
ihk_ausbildungsnachweis_utilities/certificate_builder.py
ihk_ausbildungsnachweis_utilities/checker.py
ihk_ausbildungsnachweis_utilities/py.typed
ihk_ausbildungsnachweis_utilities/signator.py
ihk_ausbildungsnachweis_utilities/starter.py
ihk_ausbildungsnachweis_utilities/schemas/ausbildungsnachweis.xsd
ihk_ausbildungsnachweis_utilities/schemas/profile.json
ihk_ausbildungsnachweis_utilities/templates/template_ausbildungsnachweis.docx
ihk_ausbildungsnachweis_utilities/templates/template_ausbildungsnachweis_with_cell_numbering.docx
tests/__init__.py
tests/test_api.py
tests/test_cli_parser.py
ihk_ausbildungsnachweis_utilities-0.2.5.dist-info/METADATA
ihk_ausbildungsnachweis_utilities-0.2.5.dist-info/WHEEL
ihk_ausbildungsnachweis_utilities-0.2.5.dist-info/entry_points.txt
ihk_ausbildungsnachweis_utilities-0.2.5.dist-info/top_level.txt
ihk_ausbildungsnachweis_utilities-0.2.5.dist-info/RECORD
