Metadata-Version: 2.1
Name: ihk-ausbildungsnachweis-utilities
Version: 0.2.5
Summary: Utilities to generate IHK Ausbildungsnachweise PDFs from human readable input format and sign them.
Home-page: https://github.com/twyleg/ausbildungsnachweis_utils
Author: Torsten Wylegala
Author-email: mail@twyleg.de
License: GPL 3.0
Keywords: ihk ausbildungsnachweis pdf signature
Requires-Dist: swig ~=4.1.1
Requires-Dist: wheel ~=0.41.2
Requires-Dist: PyMuPDF ~=1.23.3
Requires-Dist: python-docx ~=0.8.11
Requires-Dist: cryptography ~=41.0.3
Requires-Dist: asn1crypto ~=1.5.1
Requires-Dist: certvalidator ~=0.11.1
Requires-Dist: lxml ~=4.9.3
Requires-Dist: pykcs11 ~=1.5.12
Requires-Dist: Pillow ~=10.0.0
Requires-Dist: endesive ~=2.0.16
Requires-Dist: xmlschema ~=2.3.1
Requires-Dist: jsonschema ~=4.18.4
Requires-Dist: types-jsonschema ~=4.17.0.10
Requires-Dist: lxml-stubs ~=0.4.0
